dbbasic_screenshot/__init__.py
dbbasic_screenshot/__main__.py
dbbasic_screenshot-0.1.0.dist-info/licenses/LICENSE
dbbasic_screenshot-0.1.0.dist-info/METADATA
dbbasic_screenshot-0.1.0.dist-info/WHEEL
dbbasic_screenshot-0.1.0.dist-info/entry_points.txt
dbbasic_screenshot-0.1.0.dist-info/top_level.txt
dbbasic_screenshot-0.1.0.dist-info/RECORD
