Metadata-Version: 2.4
Name: dbbasic-screenshot
Version: 0.1.0
Summary: Fast screenshot annotation tool for macOS
Author: askrobots
License: MIT
Project-URL: Homepage, https://github.com/askrobots/dbbasic-screenshot
Project-URL: Repository, https://github.com/askrobots/dbbasic-screenshot
Project-URL: Issues, https://github.com/askrobots/dbbasic-screenshot/issues
Keywords: screenshot,annotation,macos,drawing,tool
Classifier: Development Status :: 4 - Beta
Classifier: Intended Audience :: End Users/Desktop
Classifier: License :: OSI Approved :: MIT License
Classifier: Operating System :: MacOS
Classifier: Programming Language :: Python :: 3
Classifier: Programming Language :: Python :: 3.7
Classifier: Programming Language :: Python :: 3.8
Classifier: Programming Language :: Python :: 3.9
Classifier: Programming Language :: Python :: 3.10
Classifier: Programming Language :: Python :: 3.11
Classifier: Topic :: Multimedia :: Graphics :: Capture :: Screen Capture
Classifier: Topic :: Multimedia :: Graphics :: Editors
Requires-Python: >=3.7
License-File: LICENSE
Requires-Dist: pillow>=10.0.0
Requires-Dist: PyQt5>=5.15.0
Dynamic: license-file
